org/__init__.py
org/codeforrussia/__init__.py
org/codeforrussia/selector/__init__.py
org/codeforrussia/selector/config/__init__.py
org/codeforrussia/selector/config/global_config.py
org/codeforrussia/selector/standardizer/__init__.py
org/codeforrussia/selector/standardizer/common.py
org/codeforrussia/selector/standardizer/election_layers.py
org/codeforrussia/selector/standardizer/standardizer_registry_factory.py
org/codeforrussia/selector/standardizer/custom/__init__.py
org/codeforrussia/selector/standardizer/custom/shpilkin_format.py
org/codeforrussia/selector/standardizer/recognizers/__init__.py
org/codeforrussia/selector/standardizer/recognizers/election_attribute_recognizer.py
org/codeforrussia/selector/standardizer/recognizers/protocol_field_recognizer_registry_factory.py
org/codeforrussia/selector/standardizer/recognizers/protocol_field_recognizers.py
org/codeforrussia/selector/standardizer/recognizers/similarity/__init__.py
org/codeforrussia/selector/standardizer/recognizers/similarity/train.py
org/codeforrussia/selector/standardizer/schemas/__init__.py
org/codeforrussia/selector/standardizer/schemas/schema_registry_db.json
org/codeforrussia/selector/standardizer/schemas/schema_registry_factory.py
org/codeforrussia/selector/standardizer/schemas/common/__init__.py
org/codeforrussia/selector/standardizer/schemas/common/election_1_0.avsc
org/codeforrussia/selector/standardizer/schemas/federal/__init__.py
org/codeforrussia/selector/standardizer/schemas/federal/state_duma_1_0.avsc
org/codeforrussia/selector/standardizer/schemas/municipal/__init__.py
org/codeforrussia/selector/standardizer/schemas/municipal/deputy_city_1_0.avsc
org/codeforrussia/selector/standardizer/schemas/regional/__init__.py
org/codeforrussia/selector/standardizer/schemas/regional/deputy_1_0.avsc
org/codeforrussia/selector/standardizer/schemas/regional/head_1_0.avsc
org/codeforrussia/selector/utils/__init__.py
org/codeforrussia/selector/utils/file.py
org/codeforrussia/selector/utils/gcs.py
selector_standardizers-0.8.3.dist-info/LICENSE
selector_standardizers-0.8.3.dist-info/METADATA
selector_standardizers-0.8.3.dist-info/WHEEL
selector_standardizers-0.8.3.dist-info/top_level.txt
selector_standardizers-0.8.3.dist-info/RECORD
