Metadata-Version: 2.1
Name: selector-standardizers
Version: 0.8.3
Summary: Electoral Data Standardization classes for the Selector project
Home-page: https://github.com/Code-for-Russia/selector-pipeline
Author: Nikita Zhiltsov
Author-email: mail@codeforrussia.org
License: UNKNOWN
Project-URL: Bug Tracker, https://github.com/Code-for-Russia/selector-pipeline/issues
Platform: UNKNOWN
Classifier: Programming Language :: Python :: 3
Classifier: License :: OSI Approved :: MIT License
Classifier: Operating System :: OS Independent
Requires-Python: >=3.7
License-File: LICENSE
Requires-Dist: pytest (>=6.2.4)
Requires-Dist: fastavro (>=1.4.0)
Requires-Dist: jsonlines (>=2.0.0)
Requires-Dist: dataclasses (>=0.6)
Requires-Dist: sentence-transformers (>=1.2.0)
Requires-Dist: scikit-learn (>=0.24.2)
Requires-Dist: google-cloud-storage (>=1.38.0)
